odoo/addons/ssi_transaction_queue_mixin/README.rst
odoo/addons/ssi_transaction_queue_mixin/__init__.py
odoo/addons/ssi_transaction_queue_mixin/__manifest__.py
odoo/addons/ssi_transaction_queue_mixin/models/__init__.py
odoo/addons/ssi_transaction_queue_mixin/models/mixin_transaction_queue.py
odoo/addons/ssi_transaction_queue_mixin/static/description/icon.png
odoo/addons/ssi_transaction_queue_mixin/templates/mixin_transaction_queue_templates.xml
odoo14_addon_ssi_transaction_queue_mixin-14.0.1.0.0.dist-info/METADATA
odoo14_addon_ssi_transaction_queue_mixin-14.0.1.0.0.dist-info/WHEEL
odoo14_addon_ssi_transaction_queue_mixin-14.0.1.0.0.dist-info/top_level.txt
odoo14_addon_ssi_transaction_queue_mixin-14.0.1.0.0.dist-info/RECORD
